LICENSE
README.rst
setup.cfg
setup.py
src/coincap_hedera_agent_kit_plugin.egg-info/PKG-INFO
src/coincap_hedera_agent_kit_plugin.egg-info/SOURCES.txt
src/coincap_hedera_agent_kit_plugin.egg-info/dependency_links.txt
src/coincap_hedera_agent_kit_plugin.egg-info/requires.txt
src/coincap_hedera_agent_kit_plugin.egg-info/top_level.txt
src/coincap_hedera_plugin/__init__.py
src/coincap_hedera_plugin/coincap_plugin/__init__.py
src/coincap_hedera_plugin/coincap_plugin/plugin.py
src/coincap_hedera_plugin/coincap_plugin/tool.py