Metadata-Version: 2.4
Name: coincap-hedera-agent-kit-plugin
Version: 0.8
Home-page: https://github.com/henrytongv/coincap-hedera-plugin-py
Author: Henry Tong
Author-email: taksantong@gmail.com
License: MIT
Keywords: hedera agent-kit coincap web3
License-File: LICENSE
Requires-Dist: hedera-agent-kit
Requires-Dist: requests
Dynamic: author
Dynamic: author-email
Dynamic: description
Dynamic: description-content-type
Dynamic: home-page
Dynamic: keywords
Dynamic: license
Dynamic: license-file
Dynamic: requires-dist
